robogate/__init__.py
robogate/actions.py
robogate/models.py
robogate/robogate.py
robogate/robot.py
robogate-1.6.0.dist-info/METADATA
robogate-1.6.0.dist-info/WHEEL
robogate-1.6.0.dist-info/top_level.txt
robogate-1.6.0.dist-info/RECORD
